meatoo_client
