Metadata-Version: 1.0
Name: meatoo
Version: 0.1.1
Summary: Command-line client for Gentoo's Meatoo using XML-RPC.
Home-page: http://tools.assembla.com/meatoo/
Author: Rob Cakebread
Author-email: gentoodev a t gmail . com
License: GPL-2
Keywords: gentoo ebuilds PyPI freshmeat
Platform: UNKNOWN
Classifier: Development Status :: 4 - Beta
Classifier: Intended Audience :: Developers
Classifier: License :: OSI Approved :: GNU General Public License (GPL)
Classifier: Programming Language :: Python
Classifier: Topic :: Software Development :: Libraries :: Python Modules
